MANIFEST.in
README.md
setup.py
canopy_toolkit/__init__.py
canopy_toolkit/__version__.py
canopy_toolkit.egg-info/PKG-INFO
canopy_toolkit.egg-info/SOURCES.txt
canopy_toolkit.egg-info/dependency_links.txt
canopy_toolkit.egg-info/requires.txt
canopy_toolkit.egg-info/top_level.txt
canopy_toolkit/api/__init__.py
canopy_toolkit/api/base.py
canopy_toolkit/api/canopy.py
canopy_toolkit/api/exceptions.py
canopy_toolkit/api/websocket.py
canopy_toolkit/database/__init__.py
canopy_toolkit/database/abstract.py
canopy_toolkit/database/asyncpg.py
canopy_toolkit/database/psycopg2.py
canopy_toolkit/utils/__init__.py
canopy_toolkit/utils/aes_encryption.py
canopy_toolkit/vault/__init__.py
canopy_toolkit/vault/client.py